steve/__init__.py
steve/insults.py
smack_talk_steve-0.0.4.dist-info/LICENSE.txt
smack_talk_steve-0.0.4.dist-info/METADATA
smack_talk_steve-0.0.4.dist-info/WHEEL
smack_talk_steve-0.0.4.dist-info/top_level.txt
smack_talk_steve-0.0.4.dist-info/RECORD
