Metadata-Version: 2.1
Name: smack-talk-steve
Version: 0.0.4
Summary: Steve talks smack to fools
Home-page: https://github.com/msmith-pdc/smack-talk-steve
Author: M Smith
Author-email: msmith@pdc.org
License: UNKNOWN
Platform: UNKNOWN
Classifier: Programming Language :: Python :: 3
Classifier: License :: OSI Approved :: MIT License
Classifier: Operating System :: OS Independent
Requires-Python: >=3.9
License-File: LICENSE.txt
Requires-Dist: numpy
